scCPEP/__init__.py
scCPEP/dataloading_utils.py
scCPEP/method_utils.py
scCPEP/pareto_ensemble_pruning.py
scCPEP/sccpep.py
scCPEP_pkg/__init__.py
scCPEP-1.0.0.dist-info/LICENSE
scCPEP-1.0.0.dist-info/METADATA
scCPEP-1.0.0.dist-info/WHEEL
scCPEP-1.0.0.dist-info/top_level.txt
scCPEP-1.0.0.dist-info/RECORD
