Metadata-Version: 2.1
Name: scCPEP
Version: 1.0.0
Summary: scCPEP
Home-page: https://github.com/IrisQi7/scCPEP
Author: Qi Qi
Author-email: qiqi20@mails.jlu.edu.cn
License: MIT
Classifier: Operating System :: OS Independent
Classifier: Topic :: Scientific/Engineering :: Artificial Intelligence
Classifier: Programming Language :: Python :: 3.7
License-File: LICENSE
